MANIFEST.in
README.rst
setup.py
src/test.py
src/PyRibbonBridge.egg-info/PKG-INFO
src/PyRibbonBridge.egg-info/SOURCES.txt
src/PyRibbonBridge.egg-info/dependency_links.txt
src/PyRibbonBridge.egg-info/requires.txt
src/PyRibbonBridge.egg-info/top_level.txt
src/ribbonbridge/__init__.py
src/ribbonbridge/nanopb_pb2.py
src/ribbonbridge/rpc_pb2.py