Metadata-Version: 1.0
Name: PyRibbonBridge
Version: 0.0.7
Summary: This is a pure Python implementation of ribbon-bridge: An RPC Framework http://github.com/BaroboRobotics/ribbon-bridge
Home-page: http://github.com/BaroboRobotics/PyRibbonBridge
Author: David Ko
Author-email: david@barobo.com
License: UNKNOWN
Platform: UNKNOWN
